setup.py
corkboard/__init__.py
corkboard/corkboard.js
corkboard.egg-info/PKG-INFO
corkboard.egg-info/SOURCES.txt
corkboard.egg-info/dependency_links.txt
corkboard.egg-info/top_level.txt