Metadata-Version: 1.1
Name: corkboard
Version: 0.1.0
Summary: A Jupyter notebook extension to hide code, prompts and outputs.
Home-page: https://github.com/kirbs-/corkboard
Author: Chris Kirby
Author-email: kirbycm@gmail.com
License: UNKNOWN
Keywords: jupyter notebook presentation
Platform: UNKNOWN
Classifier: Development Status :: 3 - Alpha
Classifier: Intended Audience :: Developers
Classifier: Topic :: Scientific/Engineering
Classifier: License :: OSI Approved :: MIT License
Classifier: Programming Language :: Python :: 2.7
Classifier: Programming Language :: Python :: 3.3
Classifier: Programming Language :: Python :: 3.4
Classifier: Programming Language :: Python :: 3.5
